ohmytmp_plugins/taggy/__init__.py
ohmytmp_plugins/taggy/taggy.py
ohmytmp_taggy-0.0.2.dist-info/LICENSE
ohmytmp_taggy-0.0.2.dist-info/METADATA
ohmytmp_taggy-0.0.2.dist-info/WHEEL
ohmytmp_taggy-0.0.2.dist-info/top_level.txt
ohmytmp_taggy-0.0.2.dist-info/RECORD
