Metadata-Version: 2.1
Name: ohmytmp-taggy
Version: 0.0.2
Summary: ohmytmp plugin taggy
Author-email: userElaina <userelaina@pm.me>
Maintainer-email: userElaina <userelaina@pm.me>
License: MIT License
Project-URL: Homepage, https://github.com/ohmytmp/plugin-taggy
Project-URL: Bug Reports, https://github.com/ohmytmp/plugin-taggy/issues
Project-URL: Source, https://github.com/ohmytmp/plugin-taggy
Keywords: ohmytmp
Classifier: License :: OSI Approved :: MIT License
Classifier: Programming Language :: Python :: 3
Requires-Python: >=3.7
License-File: LICENSE
Requires-Dist: ohmytmp
